CONTRIBUTING.md
LICENSE
MANIFEST.in
Makefile
README.md
pyproject.toml
setup.py
valparse/__init__.py
valparse/util.py
valparse/valparse.py
valparse.egg-info/PKG-INFO
valparse.egg-info/SOURCES.txt
valparse.egg-info/dependency_links.txt
valparse.egg-info/requires.txt
valparse.egg-info/top_level.txt
valparse/tests/test_parser.py
valparse/tests/test_vgerror.py
valparse/tests/data/.gitignore
valparse/tests/data/bad-test.xml
valparse/tests/data/bad.supp
valparse/tests/data/test.supp