Metadata-Version: 2.1
Name: valparse
Version: 0.2.1
Summary: Package to parse Valgrind XML files.
Author-email: Tal Zussman <tz2294@columbia.edu>
License: MIT License
Project-URL: repository, https://github.com/tzussman/valparse
Requires-Python: >=3.7
Provides-Extra: develop
License-File: LICENSE
